{
    "REGISTRATIONNO": "P65097001048",
    "FACILITYNAME": "利偉商行",
    "COUNTY": "嘉義市",
    "COUNTYCODE": "",
    "DOCUMENTNO": "21-114-050012",
    "PENALTYYEAR": "2025",
    "PENALTYDATE": "2025\/05\/09",
    "TRANSGRESSDATE": "2025\/04\/24",
    "TRANSGRESSLAW": "空氣污染防制法第36條第1項",
    "PENALTYMONEY": "NT$10,000",
    "ISPETITION": "否",
    "PETITIONAGENCY": "",
    "PETITIONRESULTS": "",
    "APPEALRESCIND": "",
    "UPDATETIME": "2025\/07\/16 21:15",
    "IMPROVEDEADLINE": "",
    "INSPECTIONCONDITION": "",
    "TRANSGRESSNAME": "利偉商行",
    "TRANSGRESSCONTROLID": "P65097001048",
    "TRANSGRESSSTATE": "貴行所有自用大貨車(車號：KEH-3**8)經嘉義市政府環境保護局路邊攔檢，檢驗不透光率達2.7m-1，超過排放標準1.2m-1。",
    "ILLEGALMONEY": "NT$0",
    "ISIMPROVE": "不須改善",
    "Source": "ERDB",
    "FACUNIFORMNO": "64904475",
    "LAWSUITDATE1": "",
    "TRACKILLEGALMONEY": "NT$0",
    "INSPECTIONDATETIMES": "",
    "PENALTYKIND": "罰鍰(非連續處罰)",
    "ISIMPORTANT": "否",
    "PAYMENTSTATE": "無分期已繳清",
    "ISREMINDER": "否",
    "ISADMINCOURT": "否",
    "IS_SERIES_FIRST": true,
    "SERIES_FIRST_DEPARTMENT_ID": "",
    "SERIES_FIRST_DEPARTMENT_NAME": "",
    "SERIES_FIRST_PENALTY_ID": "",
    "FACADDRESS": "雲林縣水林鄉西井村西井路一○五之二號一樓",
    "TRANSGRESSADDRESS": "嘉義市世賢路2段196巷口旁",
    "SUBJECT": "罰鍰新臺幣10000元整。處環境講習1小時整。",
    "GISTDEFINE": "違反空氣污染防制法第36條第1項之規定，並依空氣污染防制法第66條第1項第1款裁處。依環境教育法第23條第2款之規定裁處環境講習",
    "ISREDUCEMONEY": "",
    "TRANSGRESSTYPE": "移動污染",
    "ALLOW_REWORK_DATA": "-",
    "created_at": "2025-07-23 14:48:26"
}