{
    "REGISTRATIONNO": "G37A7640",
    "FACILITYNAME": "奕昌清除有限公司",
    "COUNTY": "宜蘭縣",
    "COUNTYCODE": "",
    "DOCUMENTNO": "44-113-120001",
    "PENALTYYEAR": "2024",
    "PENALTYDATE": "2024\/12\/19",
    "TRANSGRESSDATE": "2024\/03\/16",
    "TRANSGRESSLAW": "廢棄物清理法第42條，公民營廢棄物清除處理機構許可管理辦法第18條第1項",
    "PENALTYMONEY": "NT$12,000",
    "ISPETITION": "否",
    "PETITIONAGENCY": "",
    "PETITIONRESULTS": "",
    "APPEALRESCIND": "",
    "UPDATETIME": "2025\/07\/02 21:15",
    "IMPROVEDEADLINE": "2024\/03\/27",
    "INSPECTIONCONDITION": "",
    "TRANSGRESSNAME": "奕昌清除有限公司",
    "TRANSGRESSCONTROLID": "G37A7640",
    "TRANSGRESSSTATE": "本局113年3月16日查獲OOOO有限公司所有車輛（車號：XXX-OO）自宜蘭縣蘇澳鎮文化段XXX及XXX地號載運土木或建築廢棄物混合物至宜蘭縣蘇澳鎮新隘段XXX及XXX地號分類、轉運，惟貴公司未設置貯存場或轉運站，貴公司未依公民營廢棄物清除處理機構許可管理辦法第18條規定，依審查通過之申請文件內容辦理廢棄物之清除、貯存、處理，此舉核已違反廢棄物清理法第42條規定。",
    "ILLEGALMONEY": "NT$0",
    "ISIMPROVE": "已改善完成",
    "Source": "ERDB",
    "FACUNIFORMNO": "53397796",
    "LAWSUITDATE1": "",
    "TRACKILLEGALMONEY": "NT$0",
    "INSPECTIONDATETIMES": "",
    "PENALTYKIND": "罰鍰(非連續處罰)，限期改善",
    "ISIMPORTANT": "否",
    "PAYMENTSTATE": "無分期已繳清",
    "ISREMINDER": "否",
    "ISADMINCOURT": "是",
    "IS_SERIES_FIRST": true,
    "SERIES_FIRST_DEPARTMENT_ID": "",
    "SERIES_FIRST_DEPARTMENT_NAME": "",
    "SERIES_FIRST_PENALTY_ID": "",
    "FACADDRESS": "宜蘭縣冬山鄉太和村太和路一三三巷一五○弄四三號一樓",
    "TRANSGRESSADDRESS": "宜蘭縣蘇澳鎮新隘段352及353地號",
    "SUBJECT": "罰鍰新臺幣12000元整。限改日期：113年03月27日。處環境講習2小時整。",
    "GISTDEFINE": "違反廢棄物清理法第42條及公民營廢棄物清除處理機構許可管理辦法第18條第1項之規定，並依廢棄物清理法第55條第1款裁處。依環境教育法第23條第2款之規定裁處環境講習",
    "ISREDUCEMONEY": "",
    "TRANSGRESSTYPE": "廢棄物清除處理機構",
    "ALLOW_REWORK_DATA": "-"
}