{
    "REGISTRATIONNO": "J55C4238",
    "FACILITYNAME": "振鈁有限公司",
    "COUNTY": "新竹縣",
    "COUNTYCODE": null,
    "DOCUMENTNO": "30-114-100001",
    "PENALTYYEAR": "2025",
    "PENALTYDATE": "2025\/10\/13",
    "TRANSGRESSDATE": "2025\/06\/02",
    "TRANSGRESSLAW": "水污染防治法第7條第1項",
    "PENALTYMONEY": "NT$165,000",
    "ISPETITION": "是",
    "PETITIONAGENCY": "",
    "PETITIONRESULTS": "",
    "APPEALRESCIND": "",
    "UPDATETIME": "2025\/12\/16 22:04",
    "IMPROVEDEADLINE": "2025\/07\/25",
    "INSPECTIONCONDITION": "",
    "TRANSGRESSNAME": "振鈁有限公司",
    "TRANSGRESSCONTROLID": "J55C4238",
    "TRANSGRESSSTATE": "該事業於114年6月2日進行廢（污）水處理設施及污泥處理設施之功能測試，本局前往會同於放流口採集水樣送驗，結果其中化學需氧量(COD)測值為126mg\/L逾放流水準限值(100mg\/L)，已涉違反水污染防治法第7條規定。",
    "ILLEGALMONEY": "NT$0",
    "ISIMPROVE": "已改善完成",
    "Source": "ERDB",
    "FACUNIFORMNO": "12644225",
    "LAWSUITDATE1": "2025\/11\/03",
    "TRACKILLEGALMONEY": "NT$0",
    "INSPECTIONDATETIMES": "",
    "PENALTYKIND": "罰鍰(非連續處罰)，限期改善",
    "ISIMPORTANT": "否",
    "PAYMENTSTATE": "無分期已繳清",
    "ISREMINDER": "否",
    "ISADMINCOURT": "否",
    "IS_SERIES_FIRST": false,
    "SERIES_FIRST_DEPARTMENT_ID": "11",
    "SERIES_FIRST_DEPARTMENT_NAME": "新竹縣",
    "SERIES_FIRST_PENALTY_ID": "30-114-040010",
    "FACADDRESS": "新竹縣竹北市泰和里環北路二段二四三巷二六號",
    "TRANSGRESSADDRESS": "新竹縣竹北市泰和里環北路二段二四三巷二六號",
    "SUBJECT": "罰鍰新臺幣165000元整。限改日期：114年07月25日。處環境講習2小時整。",
    "GISTDEFINE": "違反水污染防治法第7條第1項規定，並依水污染防治法第40條第1項暨「違反水污染防治法罰鍰額度裁罰準則」裁處。依環境教育法第23條第2款之規定裁處環境講習",
    "ISREDUCEMONEY": "",
    "TRANSGRESSTYPE": "水污染",
    "ALLOW_REWORK_DATA": "-"
}