{
    "REGISTRATIONNO": "J61A0741",
    "FACILITYNAME": "台灣德瑞特生物科技股份有限公司",
    "COUNTY": "新竹縣",
    "COUNTYCODE": "",
    "DOCUMENTNO": "40-106-030004",
    "PENALTYYEAR": "2017",
    "PENALTYDATE": "2017\/03\/06",
    "TRANSGRESSDATE": "2016\/07\/12",
    "TRANSGRESSLAW": "廢棄物清理法第31條第1項第2款",
    "PENALTYMONEY": "NT$60,000",
    "ISPETITION": "否",
    "PETITIONAGENCY": "",
    "PETITIONRESULTS": "",
    "APPEALRESCIND": "",
    "UPDATETIME": "2025\/02\/04 20:30",
    "IMPROVEDEADLINE": "",
    "INSPECTIONCONDITION": "",
    "TRANSGRESSNAME": "台灣德瑞特生物科技股份有限公司 ",
    "TRANSGRESSCONTROLID": "J61A0741",
    "TRANSGRESSSTATE": "本局勾稽事業廢棄物網路申報異常辦理，發現貴公司化學(農化)實驗作業程序(代碼:850001)中廢棄之微生物培養物、菌株及相關生物製品(代碼:C-0501)，及實驗室廢棄物(代碼:C-0507)，自105年1月起至3月止，未依規定至行政院環境保護署事業廢棄物申報及管理資訊系統進行廢棄物之相關申報，已違反廢棄物清理法第31條第1項第2款規定。",
    "ILLEGALMONEY": "NT$0",
    "ISIMPROVE": "不須改善",
    "Source": "ERDB",
    "FACUNIFORMNO": "27648038",
    "LAWSUITDATE1": "",
    "TRACKILLEGALMONEY": "NT$0",
    "INSPECTIONDATETIMES": "",
    "PENALTYKIND": "罰鍰(非連續處罰)",
    "ISIMPORTANT": "",
    "PAYMENTSTATE": "無分期已繳清",
    "ISREMINDER": "否",
    "ISADMINCOURT": "否",
    "IS_SERIES_FIRST": true,
    "SERIES_FIRST_DEPARTMENT_ID": "",
    "SERIES_FIRST_DEPARTMENT_NAME": "",
    "SERIES_FIRST_PENALTY_ID": "",
    "FACADDRESS": "新竹縣新豐鄉新豐村新和路九六之一號四樓",
    "TRANSGRESSADDRESS": "新竹縣新豐鄉新豐村新和路九六之一號四樓 ",
    "SUBJECT": "罰鍰新臺幣60000元整。處環境講習2小時整。",
    "GISTDEFINE": "違反廢棄物清理法第31條第1項第2款之規定，並依廢棄物清理法第53條裁處。依環境教育法第23條第2款之規定裁處環境講習",
    "ISREDUCEMONEY": "",
    "TRANSGRESSTYPE": "事業廢棄物",
    "ALLOW_REWORK_DATA": "-"
}