{
    "REGISTRATIONNO": "E15099022849",
    "FACILITYNAME": "百麒洗衣實業有限公司",
    "COUNTY": "高雄市",
    "COUNTYCODE": "",
    "DOCUMENTNO": "30-112-050002",
    "PENALTYYEAR": "2023",
    "PENALTYDATE": "2023\/05\/09",
    "TRANSGRESSDATE": "2023\/03\/21",
    "TRANSGRESSLAW": "水污染防治法第30條第1項第2款",
    "PENALTYMONEY": "NT$30,000",
    "ISPETITION": "否",
    "PETITIONAGENCY": "",
    "PETITIONRESULTS": "",
    "APPEALRESCIND": "",
    "UPDATETIME": "2025\/02\/04 20:30",
    "IMPROVEDEADLINE": "",
    "INSPECTIONCONDITION": "",
    "TRANSGRESSNAME": "百麒洗衣實業有限公司",
    "TRANSGRESSCONTROLID": "E15099022849",
    "TRANSGRESSSTATE": "案係本局接獲民眾檢舉仁武區仁雄路橋下有白色泡泡水，經本局派員稽查發現橋下有一水流注入大排，致水面有白色泡沫之情事。經巡上游發現為貴公司經營洗衣業，現場有7台100kg，1台50kg洗衣機，稽查當時正常洗衣作業中且所產生之洗衣廢水未經妥善處理直接排放，致仁雄路橋下白色泡泡之污染情事，污染事實明確，依據上述污染事實，已違反水污染防治法第30條第1項第2款之規定",
    "ILLEGALMONEY": "NT$0",
    "ISIMPROVE": "不須改善",
    "Source": "ERDB",
    "FACUNIFORMNO": "53570676",
    "LAWSUITDATE1": "",
    "TRACKILLEGALMONEY": "NT$0",
    "INSPECTIONDATETIMES": "",
    "PENALTYKIND": "罰鍰(非連續處罰)",
    "ISIMPORTANT": "否",
    "PAYMENTSTATE": "無分期已繳清",
    "ISREMINDER": "否",
    "ISADMINCOURT": "否",
    "IS_SERIES_FIRST": true,
    "SERIES_FIRST_DEPARTMENT_ID": "",
    "SERIES_FIRST_DEPARTMENT_NAME": "",
    "SERIES_FIRST_PENALTY_ID": "",
    "FACADDRESS": "高雄市鳳山區瑞興路三七六號一樓",
    "TRANSGRESSADDRESS": "高雄市仁武區八德西路81巷63號",
    "SUBJECT": "罰鍰新臺幣30000元整。處環境講習2小時整。",
    "GISTDEFINE": "違反水污染防治法第30條第1項規定，並依水污染防治法第52條第1項之規定裁處。\n依環境教育法第23條之規定裁處環境講習。\n依環境教育法第23條第2款之規定裁處環境講習",
    "ISREDUCEMONEY": "",
    "TRANSGRESSTYPE": "水污染",
    "ALLOW_REWORK_DATA": "-"
}