{
    "REGISTRATIONNO": "E1604183",
    "FACILITYNAME": "明德食品工業股份有限公司",
    "COUNTY": "高雄市",
    "COUNTYCODE": "",
    "DOCUMENTNO": "34-106-110002",
    "PENALTYYEAR": "2017",
    "PENALTYDATE": "2017\/11\/06",
    "TRANSGRESSDATE": "2017\/05\/23",
    "TRANSGRESSLAW": "毒性化學物質管理法第16條第4項",
    "PENALTYMONEY": "NT$60,000",
    "ISPETITION": "否",
    "PETITIONAGENCY": "",
    "PETITIONRESULTS": "",
    "APPEALRESCIND": "",
    "UPDATETIME": "2025\/02\/04 20:30",
    "IMPROVEDEADLINE": "",
    "INSPECTIONCONDITION": "",
    "TRANSGRESSNAME": "明德食品工業股份有限公司",
    "TRANSGRESSCONTROLID": "E1604183",
    "TRANSGRESSSTATE": "該公司於106年4月28日取得鉻酸鉀毒性化學物質核可文件，並於5月22日進1瓶250公克，另於6月19日使用12.564公克，確定有實際運作行為，另查該公司於106年8月16日始加入聯防組職，已違反毒性化學物質管理法第16條第4項規定。",
    "ILLEGALMONEY": "NT$0",
    "ISIMPROVE": "不須改善",
    "Source": "ERDB",
    "FACUNIFORMNO": "88686792",
    "LAWSUITDATE1": "",
    "TRACKILLEGALMONEY": "NT$0",
    "INSPECTIONDATETIMES": "",
    "PENALTYKIND": "罰鍰(非連續處罰)",
    "ISIMPORTANT": "",
    "PAYMENTSTATE": "無分期已繳清",
    "ISREMINDER": "否",
    "ISADMINCOURT": "否",
    "IS_SERIES_FIRST": true,
    "SERIES_FIRST_DEPARTMENT_ID": "",
    "SERIES_FIRST_DEPARTMENT_NAME": "",
    "SERIES_FIRST_PENALTY_ID": "",
    "FACADDRESS": "高雄市岡山區信義里河堤路二段一二八號一樓",
    "TRANSGRESSADDRESS": "高雄市阿蓮區",
    "SUBJECT": "罰鍰新臺幣60000元整。處環境講習2小時整。",
    "GISTDEFINE": "違反毒性化學物質管理法第16條第4項之規定，並依毒性化學物質管理法第35條第1項第10款裁處。依環境教育法第23條第2款之規定裁處環境講習",
    "ISREDUCEMONEY": "",
    "TRANSGRESSTYPE": "毒性及關注化學物質",
    "ALLOW_REWORK_DATA": "-"
}