{
    "REGISTRATIONNO": "S3200446",
    "FACILITYNAME": "宗美工業股份有限公司",
    "COUNTY": "高雄市",
    "COUNTYCODE": "",
    "DOCUMENTNO": "40-111-010011",
    "PENALTYYEAR": "2022",
    "PENALTYDATE": "2022\/01\/05",
    "TRANSGRESSDATE": "2021\/09\/06",
    "TRANSGRESSLAW": "廢棄物清理法第36條第1項，事業廢棄物貯存清除處理方法及設施標準第6條第1項第4款",
    "PENALTYMONEY": "NT$6,000",
    "ISPETITION": "否",
    "PETITIONAGENCY": "",
    "PETITIONRESULTS": "",
    "APPEALRESCIND": "",
    "UPDATETIME": "2025\/07\/02 21:15",
    "IMPROVEDEADLINE": "",
    "INSPECTIONCONDITION": "",
    "TRANSGRESSNAME": "宗美工業股份有限公司",
    "TRANSGRESSCONTROLID": "S3200446",
    "TRANSGRESSSTATE": "案係本局110年9月6日派員至貴公司稽查，發現違規情形如次：廢鐵（R-1301）、廢活性碳（R-2408、D-2403）、廢潤滑油（R-1703、D-1703）、廢木材（R-0701）、廢塑膠（R-0201）、一般廢化學物質混合物（D-2399），貯存地點、容器及設施，未於明顯處以中文標示廢棄物名稱，已違反廢棄物清理法第36條第1項暨事業廢棄物貯存清除處理方式及設施標準第6條第1項第4款規定。",
    "ILLEGALMONEY": "NT$0",
    "ISIMPROVE": "不須改善",
    "Source": "ERDB",
    "FACUNIFORMNO": "88714919",
    "LAWSUITDATE1": "",
    "TRACKILLEGALMONEY": "NT$0",
    "INSPECTIONDATETIMES": "",
    "PENALTYKIND": "罰鍰(非連續處罰)",
    "ISIMPORTANT": "否",
    "PAYMENTSTATE": "無分期已繳清",
    "ISREMINDER": "否",
    "ISADMINCOURT": "否",
    "IS_SERIES_FIRST": true,
    "SERIES_FIRST_DEPARTMENT_ID": "",
    "SERIES_FIRST_DEPARTMENT_NAME": "",
    "SERIES_FIRST_PENALTY_ID": "",
    "FACADDRESS": "高雄市永安區維新里光明一巷三一之三號",
    "TRANSGRESSADDRESS": "高雄市永安區光明1巷31-3號",
    "SUBJECT": "罰鍰新臺幣6000元整。處環境講習1小時整。",
    "GISTDEFINE": "違反廢棄物清理法第36條第1項暨事業廢棄物貯存清除處理方式及設施標準第6條第1項第4款規定，爰依同法第52條裁處暨違反廢棄物清理法罰鍰額度裁罰準則(附表二項次13)規定裁處。依環境教育法第23條第2款之規定裁處環境講習",
    "ISREDUCEMONEY": "",
    "TRANSGRESSTYPE": "事業廢棄物",
    "ALLOW_REWORK_DATA": "-",
    "created_at": "2025-07-23 14:51:31"
}