{
    "REGISTRATIONNO": "K6806502",
    "FACILITYNAME": "正昇汽車運輸股份有限公司",
    "COUNTY": "苗栗縣",
    "COUNTYCODE": null,
    "DOCUMENTNO": "44-115-010003",
    "PENALTYYEAR": "2026",
    "PENALTYDATE": "2026\/01\/20",
    "TRANSGRESSDATE": "2025\/09\/22",
    "TRANSGRESSLAW": "應裝置即時追蹤系統之清運機具及其規定第8條，廢棄物清理法第31條第1項第3款",
    "PENALTYMONEY": "NT$30,000",
    "ISPETITION": "否",
    "PETITIONAGENCY": "",
    "PETITIONRESULTS": "",
    "APPEALRESCIND": "",
    "UPDATETIME": "2026\/02\/09 10:36",
    "IMPROVEDEADLINE": "",
    "INSPECTIONCONDITION": "",
    "TRANSGRESSNAME": "正昇汽車運輸股份有限公司",
    "TRANSGRESSCONTROLID": "K6806502",
    "TRANSGRESSSTATE": "經查貴公司為領有本府核發乙級廢棄物清除許可證之業者，清除廢棄物之車輛依規定須裝置即時追蹤系統(GPS)並維持運作，經查貴公司所屬列管車輛OS-41分別於114年9月22日（下午：01：52：36）及10月25日（上午：11：27：13）行駛於台86-台南市臺南交流道西出口及國3-通霄交流道南下出口，經環境部環境管理署非法棄置智慧圍籬系統勾稽比對上述車輛未依規定開啟GPS系統，無軌跡訊號傳送。",
    "ILLEGALMONEY": "NT$0",
    "ISIMPROVE": "不須改善",
    "Source": "ERDB",
    "FACUNIFORMNO": "49664449",
    "LAWSUITDATE1": "",
    "TRACKILLEGALMONEY": "NT$0",
    "INSPECTIONDATETIMES": "",
    "PENALTYKIND": "罰鍰(非連續處罰)",
    "ISIMPORTANT": "否",
    "PAYMENTSTATE": "尚未繳款",
    "ISREMINDER": "否",
    "ISADMINCOURT": "否",
    "IS_SERIES_FIRST": true,
    "SERIES_FIRST_DEPARTMENT_ID": "",
    "SERIES_FIRST_DEPARTMENT_NAME": "",
    "SERIES_FIRST_PENALTY_ID": "",
    "FACADDRESS": "苗栗縣苗栗市玉華里四鄰復興路三段一一四號",
    "TRANSGRESSADDRESS": "苗栗縣苗栗市玉清路186號",
    "SUBJECT": "罰鍰新臺幣30000元整。處環境講習2小時整。",
    "GISTDEFINE": "違反廢棄物清理法第31條第1項第3款及應裝置即時追蹤系統之清運機具及其規定第8條之規定，並依廢棄物清理法第52條裁處。依環境教育法第23條第2款之規定裁處環境講習",
    "ISREDUCEMONEY": "",
    "TRANSGRESSTYPE": "廢棄物清除處理機構",
    "ALLOW_REWORK_DATA": "-"
}