{
    "REGISTRATIONNO": "F06097029233",
    "FACILITYNAME": "佳能企業股份有限公司",
    "COUNTY": "新北市",
    "COUNTYCODE": "",
    "DOCUMENTNO": "10-108-010001",
    "PENALTYYEAR": "2019",
    "PENALTYDATE": "2019\/01\/16",
    "TRANSGRESSDATE": "2018\/12\/04",
    "TRANSGRESSLAW": "環境影響評估法第17條，違反環境影響評估法罰鍰額度裁量基準第4條",
    "PENALTYMONEY": "NT$300,000",
    "ISPETITION": "否",
    "PETITIONAGENCY": "",
    "PETITIONRESULTS": "",
    "APPEALRESCIND": "",
    "UPDATETIME": "2025\/07\/02 21:15",
    "IMPROVEDEADLINE": "",
    "INSPECTIONCONDITION": "",
    "TRANSGRESSNAME": "佳能企業股份有限公司",
    "TRANSGRESSCONTROLID": "F15097005474",
    "TRANSGRESSSTATE": "本開發案領有105莊使字第00423號使用執照，核准日期為105年9月29日，並於105年10月7日取得，惟本案銀級綠建築標章（證書字第：GB0101284(加)）於106年6月30日取得，未依本案新北市政府102年3月7日北府環規字第10213499761號公告審查結論事項二(二)「…綠建築標章則應於取得使用執照後6個月內取得…」切實執行，已違反環境影響評估法第17條規定。",
    "ILLEGALMONEY": "NT$0",
    "ISIMPROVE": "不須改善",
    "Source": "ERDB",
    "FACUNIFORMNO": "11394902",
    "LAWSUITDATE1": "",
    "TRACKILLEGALMONEY": "NT$0",
    "INSPECTIONDATETIMES": "",
    "PENALTYKIND": "罰鍰(非連續處罰)",
    "ISIMPORTANT": "否",
    "PAYMENTSTATE": "無分期已繳清",
    "ISREMINDER": "否",
    "ISADMINCOURT": "否",
    "IS_SERIES_FIRST": true,
    "SERIES_FIRST_DEPARTMENT_ID": "",
    "SERIES_FIRST_DEPARTMENT_NAME": "",
    "SERIES_FIRST_PENALTY_ID": "",
    "FACADDRESS": "新北市新莊區中環路三段二○○號一八樓",
    "TRANSGRESSADDRESS": "新北市新莊區副都心段一小段431及431-1地號等2筆土地",
    "SUBJECT": "罰鍰新臺幣300000元整。處環境講習2小時整。",
    "GISTDEFINE": "違反環境影響評估法第7條第3項及第17條規定，並依環境影響評估法第23條第1項第1款暨「違反環境影響評估法罰鍰額度裁量基準」第4點規定裁處。依環境教育法第23條第2款之規定裁處環境講習",
    "ISREDUCEMONEY": "",
    "TRANSGRESSTYPE": "環境影響評估",
    "ALLOW_REWORK_DATA": "-"
}