{
    "REGISTRATIONNO": "H49C2611",
    "FACILITYNAME": "鋐耀精工股份有限公司八德廠",
    "COUNTY": "桃園市",
    "COUNTYCODE": null,
    "DOCUMENTNO": "20-114-090019",
    "PENALTYYEAR": "2025",
    "PENALTYDATE": "2025\/09\/12",
    "TRANSGRESSDATE": "2025\/09\/04",
    "TRANSGRESSLAW": "空氣污染防制法第24條第2項",
    "PENALTYMONEY": "NT$320,000",
    "ISPETITION": "否",
    "PETITIONAGENCY": "",
    "PETITIONRESULTS": "",
    "APPEALRESCIND": "",
    "UPDATETIME": "2025\/10\/03 22:11",
    "IMPROVEDEADLINE": "2025\/12\/20",
    "INSPECTIONCONDITION": "",
    "TRANSGRESSNAME": "鋐耀精工股份有限公司八德廠",
    "TRANSGRESSCONTROLID": "H49C2611",
    "TRANSGRESSSTATE": "未取得固定污染源操作許可證，即逕行操作行為。",
    "ILLEGALMONEY": "NT$0",
    "ISIMPROVE": "待改善",
    "Source": "ERDB",
    "FACUNIFORMNO": "",
    "LAWSUITDATE1": "",
    "TRACKILLEGALMONEY": "NT$0",
    "INSPECTIONDATETIMES": "",
    "PENALTYKIND": "勒令停工，限期改善，罰鍰(非連續處罰)",
    "ISIMPORTANT": "否",
    "PAYMENTSTATE": "尚未繳款",
    "ISREMINDER": "否",
    "ISADMINCOURT": "否",
    "IS_SERIES_FIRST": true,
    "SERIES_FIRST_DEPARTMENT_ID": "",
    "SERIES_FIRST_DEPARTMENT_NAME": "",
    "SERIES_FIRST_PENALTY_ID": "",
    "FACADDRESS": "桃園市八德區和平路二七六巷三九弄三一號",
    "TRANSGRESSADDRESS": "桃園市八德區和平路276巷39弄31號",
    "SUBJECT": "罰鍰新臺幣320000元整，命貴廠粉末冶金程序停工限改日期：114年12月20日。處環境講習8小時整。",
    "GISTDEFINE": "違反空氣污染防制法第24條第2項之規定，並依空氣污染防制法第63條裁處。依環境教育法第23條第1款之規定裁處環境講習",
    "ISREDUCEMONEY": "",
    "TRANSGRESSTYPE": "固定空污",
    "ALLOW_REWORK_DATA": "-"
}