{
    "REGISTRATIONNO": "D07100000078",
    "FACILITYNAME": "經濟部水利署南區水資源分署",
    "COUNTY": "高雄市",
    "COUNTYCODE": "",
    "DOCUMENTNO": "23-107-050003",
    "PENALTYYEAR": "2018",
    "PENALTYDATE": "2018\/05\/07",
    "TRANSGRESSDATE": "2017\/11\/23",
    "TRANSGRESSLAW": "空氣污染防制法第23條第2項",
    "PENALTYMONEY": "NT$20,000",
    "ISPETITION": "否",
    "PETITIONAGENCY": "",
    "PETITIONRESULTS": "",
    "APPEALRESCIND": "",
    "UPDATETIME": "2025\/02\/04 20:30",
    "IMPROVEDEADLINE": "2018\/05\/31",
    "INSPECTIONCONDITION": "",
    "TRANSGRESSNAME": "經濟部水利署南區水資源局",
    "TRANSGRESSCONTROLID": "D07100000078",
    "TRANSGRESSSTATE": "經本局人員於106年9月7日稽查發現有「大樹堤防銜接高屏堰防洪牆及姑婆寮至大庄排水間堤內導排水路工程」(1)第一級營建工程工地內之車行路徑，實施面積未達80%、(2)車輛離開營建工地時未有效清洗車體或輪胎，其表面附著污泥等缺失，依「空氣污染防制法」第23條第2項授權訂定之「營建工程空氣污染防制設施管理辦法」第8條、第10條規定，共缺失記點8點，且依「營建工程業主違反營建工程空氣污染防制設施管理辦法之缺失記點及其處理原則」說明二第1項第2款第1目規定限期於106年9月17日完成改善。本局人員續於106年11月23日複查發現本工程再有(1)營建工地出入口未設置洗車設備，或無設置洗車空間，且未以加壓沖洗設備清洗者(原工地出入口位置已更改；新工地出入口未設置洗車設備)、(2)車輛離開營建工地時未有效清洗車體或輪胎，其表面附著污泥等缺失，依「空氣污染防制法」第23條第2項授權訂定之「營建工程空氣污染防制設施管理辦法」第10條規定，缺失記點10點，業已違反「空氣污染防制法」第23條第2項規定。",
    "ILLEGALMONEY": "NT$0",
    "ISIMPROVE": "已改善完成",
    "Source": "ERDB",
    "FACUNIFORMNO": "72068106",
    "LAWSUITDATE1": "",
    "TRACKILLEGALMONEY": "NT$0",
    "INSPECTIONDATETIMES": "",
    "PENALTYKIND": "罰鍰(非連續處罰)",
    "ISIMPORTANT": "",
    "PAYMENTSTATE": "無分期已繳清",
    "ISREMINDER": "否",
    "ISADMINCOURT": "否",
    "IS_SERIES_FIRST": true,
    "SERIES_FIRST_DEPARTMENT_ID": "",
    "SERIES_FIRST_DEPARTMENT_NAME": "",
    "SERIES_FIRST_PENALTY_ID": "",
    "FACADDRESS": "臺南市楠西區密枝里七○號",
    "TRANSGRESSADDRESS": "高雄市大樹區高屏溪右岸河川公地(河川公地圖籍第178、176、168號)",
    "SUBJECT": "罰鍰新臺幣20000元整。限改日期：107年05月31日。處環境講習2小時整。",
    "GISTDEFINE": "違反「空氣污染防制法」第23條第2項授權訂定之「營建工程空氣污染防制設施管理辦法」第10條規定，並依空氣污染防制法第56條規定裁處。依環境教育法第23條第2款之規定裁處環境講習",
    "ISREDUCEMONEY": "",
    "TRANSGRESSTYPE": "營建工程",
    "ALLOW_REWORK_DATA": "-"
}