{
    "REGISTRATIONNO": "H45097007225",
    "FACILITYNAME": "百禾紙業有限公司",
    "COUNTY": "桃園市",
    "COUNTYCODE": "",
    "DOCUMENTNO": "30-110-060039",
    "PENALTYYEAR": "2021",
    "PENALTYDATE": "2021\/06\/30",
    "TRANSGRESSDATE": "2021\/03\/19",
    "TRANSGRESSLAW": "水污染防治法第30條第1項第5款",
    "PENALTYMONEY": "NT$30,000",
    "ISPETITION": "否",
    "PETITIONAGENCY": "",
    "PETITIONRESULTS": "",
    "APPEALRESCIND": "",
    "UPDATETIME": "2025\/02\/04 20:30",
    "IMPROVEDEADLINE": "",
    "INSPECTIONCONDITION": "",
    "TRANSGRESSNAME": "百禾紙業有限公司",
    "TRANSGRESSCONTROLID": "H45097007225",
    "TRANSGRESSSTATE": "本府環境保護局於110年3月16日派員前往稽查，查獲貴公司製程印刷油墨未能有效循環處理，導致紅色油墨廢水排出至廠區前水溝，污染水溝，經限期貴公司於110年3月18日前完成改善，復經本府環境保護局110年3月19日派員前往複查，廠區前水溝仍有紅色油墨廢水殘留情事，仍未完成改善。",
    "ILLEGALMONEY": "NT$0",
    "ISIMPROVE": "不須改善",
    "Source": "ERDB",
    "FACUNIFORMNO": "97241146",
    "LAWSUITDATE1": "",
    "TRACKILLEGALMONEY": "NT$0",
    "INSPECTIONDATETIMES": "",
    "PENALTYKIND": "罰鍰(非連續處罰)",
    "ISIMPORTANT": "否",
    "PAYMENTSTATE": "無分期已繳清",
    "ISREMINDER": "否",
    "ISADMINCOURT": "否",
    "IS_SERIES_FIRST": false,
    "SERIES_FIRST_DEPARTMENT_ID": "10",
    "SERIES_FIRST_DEPARTMENT_NAME": "桃園市",
    "SERIES_FIRST_PENALTY_ID": "30-110-060037",
    "FACADDRESS": "桃園市楊梅區民有路二段五三四號",
    "TRANSGRESSADDRESS": "桃園市楊梅區員本里民有路二段534號",
    "SUBJECT": "罰鍰新臺幣30000元整。處環境講習2小時整。",
    "GISTDEFINE": "違反水污染防治法第30條第1項第5款之規定，並依水污染防治法第52條裁處。依環境教育法第23條第2款之規定裁處環境講習",
    "ISREDUCEMONEY": "",
    "TRANSGRESSTYPE": "水污染",
    "ALLOW_REWORK_DATA": "-"
}