{
    "REGISTRATIONNO": "A36097022104",
    "FACILITYNAME": "長虹建設股份有限公司",
    "COUNTY": "新北市",
    "COUNTYCODE": "",
    "DOCUMENTNO": "23-110-090004",
    "PENALTYYEAR": "2021",
    "PENALTYDATE": "2021\/09\/11",
    "TRANSGRESSDATE": "2021\/07\/15",
    "TRANSGRESSLAW": "空氣污染防制法第23條第2項，營建工程空氣污染防制設施管理辦法第7條",
    "PENALTYMONEY": "NT$100,000",
    "ISPETITION": "否",
    "PETITIONAGENCY": "",
    "PETITIONRESULTS": "",
    "APPEALRESCIND": "",
    "UPDATETIME": "2025\/02\/04 20:30",
    "IMPROVEDEADLINE": "",
    "INSPECTIONCONDITION": "",
    "TRANSGRESSNAME": "長虹建設股份有限公司",
    "TRANSGRESSCONTROLID": "A36097022104",
    "TRANSGRESSSTATE": "本局於110年7月15日15時許派員前往貴公司主辦之「長虹建設新店央泱集合住宅新建工程」(新北市新店區斯馨段33及35地號)稽查，並依「營建工程業主違反營建工程空氣污染防制設施管理辦法之缺失記點及其處理原則」，查獲物料堆置：未依規定採行覆蓋防塵布、防塵網或配合噴灑化學穩定劑等設施之一者，記缺失10點。",
    "ILLEGALMONEY": "NT$0",
    "ISIMPROVE": "不須改善",
    "Source": "ERDB",
    "FACUNIFORMNO": "04633597",
    "LAWSUITDATE1": "",
    "TRACKILLEGALMONEY": "NT$0",
    "INSPECTIONDATETIMES": "",
    "PENALTYKIND": "罰鍰(非連續處罰)",
    "ISIMPORTANT": "否",
    "PAYMENTSTATE": "無分期已繳清",
    "ISREMINDER": "否",
    "ISADMINCOURT": "否",
    "IS_SERIES_FIRST": true,
    "SERIES_FIRST_DEPARTMENT_ID": "",
    "SERIES_FIRST_DEPARTMENT_NAME": "",
    "SERIES_FIRST_PENALTY_ID": "",
    "FACADDRESS": "臺北市中正區北平東路三○號一一樓",
    "TRANSGRESSADDRESS": "新北市新店區斯馨段33及35地號",
    "SUBJECT": "罰鍰新臺幣100000元整。處環境講習2小時整。",
    "GISTDEFINE": "違反空氣污染防制法第23條第2項暨營建工程空氣污染防制設施管理辦法第7條規定，爰依空氣污染防制法第62條第1項第4款暨「公私場所固定污染源違反空氣污染防治法應處罰鍰額度裁罰準則」第3條、第4條及附表二規定裁處。依環境教育法第23條第2款之規定裁處環境講習",
    "ISREDUCEMONEY": "",
    "TRANSGRESSTYPE": "營建工程",
    "ALLOW_REWORK_DATA": "-",
    "created_at": "2025-07-23 14:51:52"
}