{
    "REGISTRATIONNO": "D27A6045",
    "FACILITYNAME": "詠源順環保有限公司",
    "COUNTY": "臺南市",
    "COUNTYCODE": "",
    "DOCUMENTNO": "30-106-110005",
    "PENALTYYEAR": "2017",
    "PENALTYDATE": "2017\/11\/09",
    "TRANSGRESSDATE": "2017\/09\/20",
    "TRANSGRESSLAW": "放流水標準第2條，水污染防治法第7條第1項",
    "PENALTYMONEY": "NT$3,000",
    "ISPETITION": "否",
    "PETITIONAGENCY": "",
    "PETITIONRESULTS": "",
    "APPEALRESCIND": "",
    "UPDATETIME": "2025\/05\/03 20:39",
    "IMPROVEDEADLINE": "",
    "INSPECTIONCONDITION": "",
    "TRANSGRESSNAME": "詠源順環保有限公司",
    "TRANSGRESSCONTROLID": "D27A6045",
    "TRANSGRESSSTATE": "貴公司從事廢油貯存或轉運站，經行政院環境保護署環境督察總隊南區環境督察大隊、內政部警政署保安警察第七總隊第三大隊第三中隊、本府環境保護局於106年9月20日派員稽查，發現貴公司將清洗地面廢水，由廠內排水溝排放於廠外地面水體，並於排放口採取水樣一組送驗，其檢驗結果未符合既設建築物污水處理設施（流量小於50立方公尺／日）放流水標準pH檢驗值5.1，標準值6-9；化學需氧量檢驗值1,920mg\/L，標準值250mg\/L；生化需氧量檢驗值230mg\/L，標準值80mg\/L；懸浮固體檢驗值125mg\/L，標準值80mg\/L。",
    "ILLEGALMONEY": "NT$0",
    "ISIMPROVE": "不須改善",
    "Source": "ERDB",
    "FACUNIFORMNO": "54080894",
    "LAWSUITDATE1": "",
    "TRACKILLEGALMONEY": "NT$0",
    "INSPECTIONDATETIMES": "",
    "PENALTYKIND": "罰鍰(非連續處罰)",
    "ISIMPORTANT": "",
    "PAYMENTSTATE": "無分期已繳清",
    "ISREMINDER": "否",
    "ISADMINCOURT": "否",
    "IS_SERIES_FIRST": true,
    "SERIES_FIRST_DEPARTMENT_ID": "",
    "SERIES_FIRST_DEPARTMENT_NAME": "",
    "SERIES_FIRST_PENALTY_ID": "",
    "FACADDRESS": "臺南市東區小東里光明街六六巷三九號六樓之九",
    "TRANSGRESSADDRESS": "臺南市仁德區太乙路27號",
    "SUBJECT": "罰鍰新臺幣3000元整。",
    "GISTDEFINE": "違反水污染防治法第7條第1項暨放流水標準第2條規定，爰依同法第41條暨違反水污染防治法罰鍰額度裁罰準則第5條第3項規定裁處。",
    "ISREDUCEMONEY": "",
    "TRANSGRESSTYPE": "水污染",
    "ALLOW_REWORK_DATA": "-"
}