{
    "REGISTRATIONNO": "J55C6393",
    "FACILITYNAME": "柏芊有限公司",
    "COUNTY": "新竹縣",
    "COUNTYCODE": "",
    "DOCUMENTNO": "20-109-110011",
    "PENALTYYEAR": "2020",
    "PENALTYDATE": "2020\/11\/16",
    "TRANSGRESSDATE": "2020\/09\/25",
    "TRANSGRESSLAW": "空氣污染防制法第32條第1項第4款",
    "PENALTYMONEY": "NT$150,000",
    "ISPETITION": "否",
    "PETITIONAGENCY": "",
    "PETITIONRESULTS": "",
    "APPEALRESCIND": "",
    "UPDATETIME": "2025\/02\/04 20:30",
    "IMPROVEDEADLINE": "2020\/10\/25",
    "INSPECTIONCONDITION": "",
    "TRANSGRESSNAME": "柏芊有限公司",
    "TRANSGRESSCONTROLID": "J55097015762",
    "TRANSGRESSSTATE": "已違反空氣污染防制法第32條第1項第4款規定",
    "ILLEGALMONEY": "NT$0",
    "ISIMPROVE": "已改善完成",
    "Source": "ERDB",
    "FACUNIFORMNO": "24382725",
    "LAWSUITDATE1": "",
    "TRACKILLEGALMONEY": "NT$0",
    "INSPECTIONDATETIMES": "",
    "PENALTYKIND": "罰鍰(非連續處罰)",
    "ISIMPORTANT": "否",
    "PAYMENTSTATE": "無分期已繳清",
    "ISREMINDER": "否",
    "ISADMINCOURT": "否",
    "IS_SERIES_FIRST": true,
    "SERIES_FIRST_DEPARTMENT_ID": "",
    "SERIES_FIRST_DEPARTMENT_NAME": "",
    "SERIES_FIRST_PENALTY_ID": "",
    "FACADDRESS": "新竹縣竹北市聯興里環北路三段二五六號一樓",
    "TRANSGRESSADDRESS": "新竹縣竹北市聯興里環北路三段二五六號一樓",
    "SUBJECT": "罰鍰新臺幣150000元整。限改日期：109年10月25日。處環境講習2小時整。",
    "GISTDEFINE": "違反空氣污染防制法第32條第1項第4款之規定，並依空氣污染防制法第67條第1項裁處。依環境教育法第23條第2款之規定裁處環境講習",
    "ISREDUCEMONEY": "",
    "TRANSGRESSTYPE": "固定空污",
    "ALLOW_REWORK_DATA": "-"
}