{
    "REGISTRATIONNO": "H4501553",
    "FACILITYNAME": "健裕實業股份有限公司",
    "COUNTY": "桃園市",
    "COUNTYCODE": "",
    "DOCUMENTNO": "20-110-030007",
    "PENALTYYEAR": "2021",
    "PENALTYDATE": "2021\/03\/11",
    "TRANSGRESSDATE": "2021\/02\/04",
    "TRANSGRESSLAW": "空氣污染防制法第24條第2項",
    "PENALTYMONEY": "NT$100,000",
    "ISPETITION": "否",
    "PETITIONAGENCY": "",
    "PETITIONRESULTS": "",
    "APPEALRESCIND": "",
    "UPDATETIME": "2025\/02\/04 20:30",
    "IMPROVEDEADLINE": "",
    "INSPECTIONCONDITION": "",
    "TRANSGRESSNAME": "健裕實業股份有限公司",
    "TRANSGRESSCONTROLID": "H4501553",
    "TRANSGRESSSTATE": "貴公司從事其他化學製品製造業，並領有本府核發固定污染源「漆料化學製造程序-油漆化學製造程序(M01)」操作許可證。經本府環境保護局派員於110年2月4日至貴公司進行查核，查核時污染源操作中，現場查核缺失如下：(1)固體、液體混合設備(濕式)E003(攪拌機)實際數量為17台，原許可核定數量為11台。(2)吸附設備(A001)壓降為250mmH2O(許可證核定150~220mmH2O)，未依許可證內容操作，核已違反空氣污染防制法相關規定。",
    "ILLEGALMONEY": "NT$0",
    "ISIMPROVE": "不須改善",
    "Source": "ERDB",
    "FACUNIFORMNO": "43700876",
    "LAWSUITDATE1": "",
    "TRACKILLEGALMONEY": "NT$0",
    "INSPECTIONDATETIMES": "",
    "PENALTYKIND": "罰鍰(非連續處罰)",
    "ISIMPORTANT": "否",
    "PAYMENTSTATE": "無分期已繳清",
    "ISREMINDER": "否",
    "ISADMINCOURT": "否",
    "IS_SERIES_FIRST": true,
    "SERIES_FIRST_DEPARTMENT_ID": "",
    "SERIES_FIRST_DEPARTMENT_NAME": "",
    "SERIES_FIRST_PENALTY_ID": "",
    "FACADDRESS": "桃園市楊梅區幼獅工業區獅二路四號",
    "TRANSGRESSADDRESS": "桃園市楊梅區幼獅工業區獅二路四號",
    "SUBJECT": "罰鍰新臺幣100000元整。處環境講習2小時整。",
    "GISTDEFINE": "違反空氣污染防制法第24條第2項之規定，並依空氣污染防制法第62條第1項第5款裁處。依環境教育法第23條第2款之規定裁處環境講習",
    "ISREDUCEMONEY": "",
    "TRANSGRESSTYPE": "固定空污",
    "ALLOW_REWORK_DATA": "-",
    "created_at": "2025-07-23 14:52:10"
}