{
    "REGISTRATIONNO": "A34097027625",
    "FACILITYNAME": "安心食品服務股份有限公司民生東路分公司",
    "COUNTY": "臺北市",
    "COUNTYCODE": null,
    "DOCUMENTNO": "41-114-102467",
    "PENALTYYEAR": "2025",
    "PENALTYDATE": "2025\/10\/29",
    "TRANSGRESSDATE": "2025\/08\/21",
    "TRANSGRESSLAW": "廢棄物清理法第27條第2款",
    "PENALTYMONEY": "NT$2,400",
    "ISPETITION": "否",
    "PETITIONAGENCY": "",
    "PETITIONRESULTS": "",
    "APPEALRESCIND": "",
    "UPDATETIME": "2025\/12\/03 22:04",
    "IMPROVEDEADLINE": "",
    "INSPECTIONCONDITION": "",
    "TRANSGRESSNAME": "安心食品服務股份有限公司民生東路分公司",
    "TRANSGRESSCONTROLID": "A34097027625",
    "TRANSGRESSSTATE": "污染地面、池溏、水溝、牆壁、樑柱、電桿、樹木、道路、橋樑或其他土地定著物。(污水污染地面)(污染程度A=2,污染特性B=1,危害程度C=1)(依「臺北市政府環境保護局各類違反環保法令案件裁罰基準」第5點經專案簽報核准。)(原X1176839作廢改告發)",
    "ILLEGALMONEY": "NT$0",
    "ISIMPROVE": "不須改善",
    "Source": "ERDB",
    "FACUNIFORMNO": "89398572",
    "LAWSUITDATE1": "",
    "TRACKILLEGALMONEY": "NT$0",
    "INSPECTIONDATETIMES": "",
    "PENALTYKIND": "罰鍰(非連續處罰)",
    "ISIMPORTANT": "否",
    "PAYMENTSTATE": "無分期已繳清",
    "ISREMINDER": "否",
    "ISADMINCOURT": "否",
    "IS_SERIES_FIRST": true,
    "SERIES_FIRST_DEPARTMENT_ID": "",
    "SERIES_FIRST_DEPARTMENT_NAME": "",
    "SERIES_FIRST_PENALTY_ID": "",
    "FACADDRESS": "臺北市松山區東昌里民生東路四段一一四號一樓",
    "TRANSGRESSADDRESS": "臺北市松山區民生東路4段114號後方",
    "SUBJECT": "罰鍰新臺幣2400元整。",
    "GISTDEFINE": "違反廢棄物清理法第27條第2款之規定，並依廢棄物清理法第50條第3款裁處。",
    "ISREDUCEMONEY": "",
    "TRANSGRESSTYPE": "一般廢棄物",
    "ALLOW_REWORK_DATA": "-"
}