{
    "REGISTRATIONNO": "B23097008888",
    "FACILITYNAME": "新圖成營造工程股份有限公司",
    "COUNTY": "臺中市",
    "COUNTYCODE": "",
    "DOCUMENTNO": "41-108-110074",
    "PENALTYYEAR": "2019",
    "PENALTYDATE": "2019\/11\/07",
    "TRANSGRESSDATE": "2019\/09\/24",
    "TRANSGRESSLAW": "廢棄物清理法第27條第2款",
    "PENALTYMONEY": "NT$4,800",
    "ISPETITION": "否",
    "PETITIONAGENCY": "",
    "PETITIONRESULTS": "",
    "APPEALRESCIND": "",
    "UPDATETIME": "2025\/07\/02 21:15",
    "IMPROVEDEADLINE": "2019\/09\/24",
    "INSPECTIONCONDITION": "",
    "TRANSGRESSNAME": "新圖成營造工程股份有限公司-海宇建設股份有限公司等13戶住宅新建工程",
    "TRANSGRESSCONTROLID": "B9505660",
    "TRANSGRESSSTATE": "本局於108年9月24日至「海宇建設股份有限公司等13戶住宅新建工程」工地稽查，該違反地點之營建工程，未妥善防範致工地車輛之輪胎附帶廢土或污泥污染路面。",
    "ILLEGALMONEY": "NT$0",
    "ISIMPROVE": "已改善完成",
    "Source": "ERDB",
    "FACUNIFORMNO": "72159963",
    "LAWSUITDATE1": "",
    "TRACKILLEGALMONEY": "NT$0",
    "INSPECTIONDATETIMES": "",
    "PENALTYKIND": "罰鍰(非連續處罰)",
    "ISIMPORTANT": "否",
    "PAYMENTSTATE": "無分期已繳清",
    "ISREMINDER": "否",
    "ISADMINCOURT": "否",
    "IS_SERIES_FIRST": true,
    "SERIES_FIRST_DEPARTMENT_ID": "",
    "SERIES_FIRST_DEPARTMENT_NAME": "",
    "SERIES_FIRST_PENALTY_ID": "",
    "FACADDRESS": "臺中市西屯區漢口路二段一三八號六樓",
    "TRANSGRESSADDRESS": "臺中市大雅區上楓段1589地號等2筆",
    "SUBJECT": "罰鍰新臺幣4800元整。限改日期：108年09月24日。",
    "GISTDEFINE": "違反廢棄物清理法第27條第2款之規定，依廢棄物清理法第50條第3款及「違反廢棄物清理法罰鍰額度裁罰準則」第2條第1款規定裁處。\n\n",
    "ISREDUCEMONEY": "",
    "TRANSGRESSTYPE": "一般廢棄物",
    "ALLOW_REWORK_DATA": "-"
}