{
    "REGISTRATIONNO": "T4900377",
    "FACILITYNAME": "東平養豬牧場",
    "COUNTY": "屏東縣",
    "COUNTYCODE": "",
    "DOCUMENTNO": "30-111-070019",
    "PENALTYYEAR": "2022",
    "PENALTYDATE": "2022\/07\/14",
    "TRANSGRESSDATE": "2022\/04\/26",
    "TRANSGRESSLAW": "水污染防治法第7條第1項",
    "PENALTYMONEY": "NT$20,020",
    "ISPETITION": "否",
    "PETITIONAGENCY": "",
    "PETITIONRESULTS": "",
    "APPEALRESCIND": "",
    "UPDATETIME": "2025\/02\/04 20:30",
    "IMPROVEDEADLINE": "2022\/08\/15",
    "INSPECTIONCONDITION": "",
    "TRANSGRESSNAME": "東平養豬牧場",
    "TRANSGRESSCONTROLID": "T4900377",
    "TRANSGRESSSTATE": "從事豬隻飼養作業，所排放廢水經採樣檢驗結果未符合放流水標準(化學需氧量檢測值1,670毫克\/公升，標準值600毫克\/公升；懸浮固體檢測值1,360毫克\/公升，標準值150毫克\/公升)，違反水污染防治法規定。",
    "ILLEGALMONEY": "NT$0",
    "ISIMPROVE": "已改善完成",
    "Source": "ERDB",
    "FACUNIFORMNO": "",
    "LAWSUITDATE1": "",
    "TRACKILLEGALMONEY": "NT$0",
    "INSPECTIONDATETIMES": "",
    "PENALTYKIND": "限期改善，罰鍰(非連續處罰)",
    "ISIMPORTANT": "否",
    "PAYMENTSTATE": "無分期已繳清",
    "ISREMINDER": "否",
    "ISADMINCOURT": "否",
    "IS_SERIES_FIRST": true,
    "SERIES_FIRST_DEPARTMENT_ID": "",
    "SERIES_FIRST_DEPARTMENT_NAME": "",
    "SERIES_FIRST_PENALTY_ID": "",
    "FACADDRESS": "屏東縣九如鄉九平段六二、一四一、一四二地號",
    "TRANSGRESSADDRESS": "屏東縣九如鄉九平段62,141,142地號",
    "SUBJECT": "罰鍰新臺幣20020元整。限改日期：111年08月15日。",
    "GISTDEFINE": "違反水污染防治法第7條第1項之規定，並依水污染防治法第40條第2項裁處。",
    "ISREDUCEMONEY": "",
    "TRANSGRESSTYPE": "水污染",
    "ALLOW_REWORK_DATA": "-"
}