{
    "REGISTRATIONNO": "C13097016629",
    "FACILITYNAME": "茂鵬實業有限公司",
    "COUNTY": "基隆市",
    "COUNTYCODE": null,
    "DOCUMENTNO": "40-115-050008",
    "PENALTYYEAR": "2026",
    "PENALTYDATE": "2026\/05\/25",
    "TRANSGRESSDATE": "2026\/04\/16",
    "TRANSGRESSLAW": "廢棄物清理法第38條第1項",
    "PENALTYMONEY": "NT$60,000",
    "ISPETITION": "否",
    "PETITIONAGENCY": "",
    "PETITIONRESULTS": "",
    "APPEALRESCIND": "",
    "UPDATETIME": "2026\/06\/16 18:01",
    "IMPROVEDEADLINE": "2026\/05\/30",
    "INSPECTIONCONDITION": "",
    "TRANSGRESSNAME": "茂鵬實業有限公司",
    "TRANSGRESSCONTROLID": "C13097016629",
    "TRANSGRESSSTATE": "依本部資源循環署112年11月8日環部循字第1126114285號公告，本案出口貨物非屬「 屬產業用料需求之事業廢棄物」之「熱塑型廢塑膠」範疇，其輸出應依廢棄物清理法第38條第1項規定申請許可。",
    "ILLEGALMONEY": "NT$0",
    "ISIMPROVE": "待改善",
    "Source": "ERDB",
    "FACUNIFORMNO": "83563666",
    "LAWSUITDATE1": "",
    "TRACKILLEGALMONEY": "NT$0",
    "INSPECTIONDATETIMES": "",
    "PENALTYKIND": "罰鍰(非連續處罰)，限期改善",
    "ISIMPORTANT": "否",
    "PAYMENTSTATE": "尚未繳款",
    "ISREMINDER": "否",
    "ISADMINCOURT": "否",
    "IS_SERIES_FIRST": true,
    "SERIES_FIRST_DEPARTMENT_ID": "",
    "SERIES_FIRST_DEPARTMENT_NAME": "",
    "SERIES_FIRST_PENALTY_ID": "",
    "FACADDRESS": "基隆市仁愛區孝二路三九號七樓之七",
    "TRANSGRESSADDRESS": "基隆市仁愛區長榮貨櫃場",
    "SUBJECT": "罰鍰新臺幣60000元整。限改日期：115年05月30日。處環境講習2小時整。",
    "GISTDEFINE": "違反廢棄物清理法第38條第1項之規定，並依廢棄物清理法第53條第3款裁處。依環境教育法第23條第2款之規定裁處環境講習",
    "ISREDUCEMONEY": "",
    "TRANSGRESSTYPE": "事業廢棄物",
    "ALLOW_REWORK_DATA": "-"
}