{
    "REGISTRATIONNO": "H53B0395",
    "FACILITYNAME": "台鎔科技材料股份有限公司",
    "COUNTY": "桃園市",
    "COUNTYCODE": null,
    "DOCUMENTNO": "44-115-040021",
    "PENALTYYEAR": "2026",
    "PENALTYDATE": "2026\/04\/28",
    "TRANSGRESSDATE": "2025\/12\/11",
    "TRANSGRESSLAW": "事業廢棄物貯存清除處理方法及設施標準第5條，廢棄物清理法第36條第1項",
    "PENALTYMONEY": "NT$60,000",
    "ISPETITION": "否",
    "PETITIONAGENCY": "",
    "PETITIONRESULTS": "",
    "APPEALRESCIND": "",
    "UPDATETIME": "2026\/06\/16 18:01",
    "IMPROVEDEADLINE": "",
    "INSPECTIONCONDITION": "",
    "TRANSGRESSNAME": "台鎔科技材料股份有限公司",
    "TRANSGRESSCONTROLID": "H53B0395",
    "TRANSGRESSSTATE": "依據廢棄物清理法第36條第2項授權訂定事業廢棄物貯存清除處理方法及設施標準第5條：「有害事業廢棄物應與一般事業廢棄物分開貯存。」規定，貴事業觀音區觀音段0093地號存放廢棄物未依規定將有害事業廢棄物與一般事業廢棄物分開貯存，核已違反前開規定。",
    "ILLEGALMONEY": "NT$0",
    "ISIMPROVE": "不須改善",
    "Source": "ERDB",
    "FACUNIFORMNO": "53831525",
    "LAWSUITDATE1": "",
    "TRACKILLEGALMONEY": "NT$0",
    "INSPECTIONDATETIMES": "",
    "PENALTYKIND": "罰鍰(非連續處罰)",
    "ISIMPORTANT": "否",
    "PAYMENTSTATE": "無分期已繳清",
    "ISREMINDER": "否",
    "ISADMINCOURT": "否",
    "IS_SERIES_FIRST": true,
    "SERIES_FIRST_DEPARTMENT_ID": "",
    "SERIES_FIRST_DEPARTMENT_NAME": "",
    "SERIES_FIRST_PENALTY_ID": "",
    "FACADDRESS": "桃園市觀音區大潭里環科路二一六號",
    "TRANSGRESSADDRESS": "桃園市觀音區環科路216號",
    "SUBJECT": "罰鍰新臺幣60000元整。處環境講習2小時整。",
    "GISTDEFINE": "違反廢棄物清理法第36條第1項及事業廢棄物貯存清除處理方法及設施標準第5條之規定，並依廢棄物清理法第53條第2款裁處。依環境教育法第23條第2款之規定裁處環境講習",
    "ISREDUCEMONEY": "",
    "TRANSGRESSTYPE": "廢棄物清除處理機構",
    "ALLOW_REWORK_DATA": "-"
}