{
    "REGISTRATIONNO": "F07097021121",
    "FACILITYNAME": "暖日子便利洗衣坊",
    "COUNTY": "新北市",
    "COUNTYCODE": "",
    "DOCUMENTNO": "22-113-050048",
    "PENALTYYEAR": "2024",
    "PENALTYDATE": "2024\/05\/28",
    "TRANSGRESSDATE": "2024\/01\/27",
    "TRANSGRESSLAW": "噪音管制法第8條第4款",
    "PENALTYMONEY": "NT$6,000",
    "ISPETITION": "否",
    "PETITIONAGENCY": "",
    "PETITIONRESULTS": "",
    "APPEALRESCIND": "",
    "UPDATETIME": "2025\/02\/04 20:30",
    "IMPROVEDEADLINE": "",
    "INSPECTIONCONDITION": "",
    "TRANSGRESSNAME": "暖日子便利洗衣坊",
    "TRANSGRESSCONTROLID": "F07097021121",
    "TRANSGRESSSTATE": "臺端經營之OOO便利洗衣坊(市招︰OOO便利洗WASH DAy)於本市第2類噪音管制區內禁止行為時段（晚上10時至翌日上午8時）使用動力機械（烘衣機）從事乾燥之商業行為，致妨害他人生活環境安寧。",
    "ILLEGALMONEY": "NT$0",
    "ISIMPROVE": "不須改善",
    "Source": "ERDB",
    "FACUNIFORMNO": "87483290",
    "LAWSUITDATE1": "",
    "TRACKILLEGALMONEY": "NT$0",
    "INSPECTIONDATETIMES": "",
    "PENALTYKIND": "罰鍰(非連續處罰)",
    "ISIMPORTANT": "",
    "PAYMENTSTATE": "無分期已繳清",
    "ISREMINDER": "否",
    "ISADMINCOURT": "否",
    "IS_SERIES_FIRST": true,
    "SERIES_FIRST_DEPARTMENT_ID": "",
    "SERIES_FIRST_DEPARTMENT_NAME": "",
    "SERIES_FIRST_PENALTY_ID": "",
    "FACADDRESS": "新北市樹林區國凱街一四六號一樓",
    "TRANSGRESSADDRESS": "新北市樹林區國凱街146號",
    "SUBJECT": "罰鍰新臺幣6000元整。處環境講習1小時整。",
    "GISTDEFINE": "違反噪音管制法第8條第4款暨新北市政府112年6月20日新北府環空字第1121157884號公告事項二、(一)規定，爰依噪音管制法第23條暨違反噪音管制法案件裁罰基準第2點附表項次1規定裁處。依環境教育法第23條第2款之規定裁處環境講習",
    "ISREDUCEMONEY": "",
    "TRANSGRESSTYPE": "噪音污染",
    "ALLOW_REWORK_DATA": "-"
}