{
    "REGISTRATIONNO": "H51097017049",
    "FACILITYNAME": "源泰開發有限公司",
    "COUNTY": "桃園市",
    "COUNTYCODE": "",
    "DOCUMENTNO": "20-112-110006",
    "PENALTYYEAR": "2023",
    "PENALTYDATE": "2023\/11\/15",
    "TRANSGRESSDATE": "2023\/09\/24",
    "TRANSGRESSLAW": "空氣污染防制法第24條第1項，空氣污染防制法第24條第2項",
    "PENALTYMONEY": "NT$520,000",
    "ISPETITION": "否",
    "PETITIONAGENCY": "",
    "PETITIONRESULTS": "",
    "APPEALRESCIND": "",
    "UPDATETIME": "2025\/02\/04 20:30",
    "IMPROVEDEADLINE": "2024\/02\/15",
    "INSPECTIONCONDITION": "",
    "TRANSGRESSNAME": "源泰開發有限公司",
    "TRANSGRESSCONTROLID": "H51097017049",
    "TRANSGRESSSTATE": "案經本府環境保護局於112年9月24日派員會同環境部北區環境管理中心及內政部警政署保安警察第七總隊前往本市新屋區埔工路325-1號稽查，貴公司於該址從事土石加工業，經量測現場土方及污泥之堆置體積已逾3,000立方公尺，係屬環境部公告第一批至第八批公私場固定污染源公告第五批第二類堆置場，惟貴公司未取得設置及操作許可證即逕行設置及操作。",
    "ILLEGALMONEY": "NT$0",
    "ISIMPROVE": "待改善",
    "Source": "ERDB",
    "FACUNIFORMNO": "42629947",
    "LAWSUITDATE1": "",
    "TRACKILLEGALMONEY": "NT$0",
    "INSPECTIONDATETIMES": "",
    "PENALTYKIND": "罰鍰(非連續處罰)，勒令停工",
    "ISIMPORTANT": "否",
    "PAYMENTSTATE": "尚未繳款",
    "ISREMINDER": "否",
    "ISADMINCOURT": "是",
    "IS_SERIES_FIRST": true,
    "SERIES_FIRST_DEPARTMENT_ID": "",
    "SERIES_FIRST_DEPARTMENT_NAME": "",
    "SERIES_FIRST_PENALTY_ID": "",
    "FACADDRESS": "桃園市平鎮區東社里明德路一一號五樓",
    "TRANSGRESSADDRESS": "桃園市新屋區埔工路325-1號",
    "SUBJECT": "罰鍰新臺幣520000元整，命貴公司堆置場停工限改日期：113年02月15日。處環境講習8小時整。",
    "GISTDEFINE": "違反空氣污染防制法第24條第1項及空氣污染防制法第24條第2項之規定，並依空氣污染防制法第63條裁處。依環境教育法第23條第2款之規定裁處環境講習",
    "ISREDUCEMONEY": "",
    "TRANSGRESSTYPE": "固定空污",
    "ALLOW_REWORK_DATA": "-",
    "created_at": "2025-07-23 14:50:13"
}