{
    "REGISTRATIONNO": "H43097011414",
    "FACILITYNAME": "弘光開發營造股份有限公司",
    "COUNTY": "桃園市",
    "COUNTYCODE": "",
    "DOCUMENTNO": "22-106-100008",
    "PENALTYYEAR": "2017",
    "PENALTYDATE": "2017\/10\/18",
    "TRANSGRESSDATE": "2017\/09\/28",
    "TRANSGRESSLAW": "噪音管制法第8條第4款",
    "PENALTYMONEY": "NT$3,000",
    "ISPETITION": "否",
    "PETITIONAGENCY": "",
    "PETITIONRESULTS": "",
    "APPEALRESCIND": "",
    "UPDATETIME": "2025\/02\/04 20:30",
    "IMPROVEDEADLINE": "",
    "INSPECTIONCONDITION": "",
    "TRANSGRESSNAME": "弘光開發營造股份有限公司",
    "TRANSGRESSCONTROLID": "H43097011414",
    "TRANSGRESSSTATE": "貴公司於違反地點從事溝渠修築工程，案經本府環境保護局於106年9月28日7時21分派員稽查，發現貴公司使用動力機械操作中，產生噪音致妨礙安寧。",
    "ILLEGALMONEY": "NT$0",
    "ISIMPROVE": "不須改善",
    "Source": "ERDB",
    "FACUNIFORMNO": "33972552",
    "LAWSUITDATE1": "",
    "TRACKILLEGALMONEY": "NT$0",
    "INSPECTIONDATETIMES": "",
    "PENALTYKIND": "罰鍰(非連續處罰)",
    "ISIMPORTANT": "",
    "PAYMENTSTATE": "無分期已繳清",
    "ISREMINDER": "否",
    "ISADMINCOURT": "否",
    "IS_SERIES_FIRST": true,
    "SERIES_FIRST_DEPARTMENT_ID": "",
    "SERIES_FIRST_DEPARTMENT_NAME": "",
    "SERIES_FIRST_PENALTY_ID": "",
    "FACADDRESS": "桃園市中壢區中央西路二段二七○之一號三樓",
    "TRANSGRESSADDRESS": "桃園市平鎮區中興路平鎮段456巷210號對面土地",
    "SUBJECT": "罰鍰新臺幣3000元整。",
    "GISTDEFINE": "違反噪音管制法第8條第4款之規定，並依噪音管制法第23條裁處。",
    "ISREDUCEMONEY": "",
    "TRANSGRESSTYPE": "噪音污染",
    "ALLOW_REWORK_DATA": "-",
    "created_at": "2025-07-23 14:54:37"
}