{
    "REGISTRATIONNO": "N19A0316",
    "FACILITYNAME": "明春窯業股份有限公司",
    "COUNTY": "彰化縣",
    "COUNTYCODE": null,
    "DOCUMENTNO": "20-115-050018",
    "PENALTYYEAR": "2026",
    "PENALTYDATE": "2026\/05\/26",
    "TRANSGRESSDATE": "2026\/04\/01",
    "TRANSGRESSLAW": "空氣污染防制法第22條第2項",
    "PENALTYMONEY": "NT$200,000",
    "ISPETITION": "否",
    "PETITIONAGENCY": "",
    "PETITIONRESULTS": "",
    "APPEALRESCIND": "",
    "UPDATETIME": "2026\/07\/03 18:01",
    "IMPROVEDEADLINE": "2026\/08\/28",
    "INSPECTIONCONDITION": "",
    "TRANSGRESSNAME": "明春窯業股份有限公司",
    "TRANSGRESSCONTROLID": "N19A0316",
    "TRANSGRESSSTATE": "本府於115年3月23日以府授環空字第1150110583號函請貴公司仍應依本府核定之指定期間(115年3月31日前)完成定檢，惟經查貴公司迄今仍未完成定期檢測，已逾本府核定之指定期間，核已違反空氣污染防制法第22條第2項規定。",
    "ILLEGALMONEY": "NT$0",
    "ISIMPROVE": "待改善",
    "Source": "ERDB",
    "FACUNIFORMNO": "24355874",
    "LAWSUITDATE1": "",
    "TRACKILLEGALMONEY": "NT$0",
    "INSPECTIONDATETIMES": "",
    "PENALTYKIND": "限期改善，罰鍰(非連續處罰)",
    "ISIMPORTANT": "否",
    "PAYMENTSTATE": "無分期已繳清",
    "ISREMINDER": "否",
    "ISADMINCOURT": "否",
    "IS_SERIES_FIRST": true,
    "SERIES_FIRST_DEPARTMENT_ID": "",
    "SERIES_FIRST_DEPARTMENT_NAME": "",
    "SERIES_FIRST_PENALTY_ID": "",
    "FACADDRESS": "彰化縣花壇鄉長春村南方一巷一一五號",
    "TRANSGRESSADDRESS": "彰化縣花壇鄉長春村南方一巷一一五號",
    "SUBJECT": "罰鍰新臺幣200000元整，請貴公司於115年8月28日期限屆滿前依固定污染源自行或委託檢測及申報管理辦法相關規定完成定期檢測，或依固定污染源設置操作及燃料使用許可證管理辦法規定提出異動申請。限改日期：115年08月28日。處環境講習2小時整。",
    "GISTDEFINE": "違反空氣污染防制法第22條第2項之規定，並依空氣污染防制法第62條第1項第3款裁處。依環境教育法第23條第2款之規定裁處環境講習",
    "ISREDUCEMONEY": "",
    "TRANSGRESSTYPE": "固定空污",
    "ALLOW_REWORK_DATA": "-"
}