{
    "REGISTRATIONNO": "S2214115",
    "FACILITYNAME": "興炳精機股份有限公司仁武廠",
    "COUNTY": "高雄市",
    "COUNTYCODE": "",
    "DOCUMENTNO": "40-110-080003",
    "PENALTYYEAR": "2021",
    "PENALTYDATE": "2021\/08\/04",
    "TRANSGRESSDATE": "2021\/03\/29",
    "TRANSGRESSLAW": "廢棄物清理法第36條第1項，事業廢棄物貯存清除處理方法及設施標準第6條第1項第4款，事業廢棄物貯存清除處理方法及設施標準第10條第1項第1款",
    "PENALTYMONEY": "NT$6,000",
    "ISPETITION": "否",
    "PETITIONAGENCY": "",
    "PETITIONRESULTS": "",
    "APPEALRESCIND": "",
    "UPDATETIME": "2025\/07\/02 21:15",
    "IMPROVEDEADLINE": "",
    "INSPECTIONCONDITION": "",
    "TRANSGRESSNAME": "興炳精機股份有限公司仁武廠",
    "TRANSGRESSCONTROLID": "S2214115",
    "TRANSGRESSSTATE": "案係民眾陳情，本局110年3月29日派員稽查，發現貴公司仁武廠於本市仁武區後庄巷117號對面水溝，發現有露天堆放一般事業廢棄物（砂土、木棧板、鐵屑、貯放於鐵製貯存槽之鐵屑），經查貯存地點容器設施未保持清潔，亦有砂土、鐵屑、切削水滲出致污染地面情事，且未以中文標示廢棄物名稱，又未設有防止地面水、雨水流入、滲出之設備或措施，堆置區貯存設施產生之廢液（切削水），未有收集或防止廢液污染地面水體之設備或措施，上開行為已違反廢棄物清理法第36條暨業廢棄物貯存清除處理方法及設施標準第6條第1項第4款、第10條第1項第1款。",
    "ILLEGALMONEY": "NT$0",
    "ISIMPROVE": "不須改善",
    "Source": "ERDB",
    "FACUNIFORMNO": "22260726",
    "LAWSUITDATE1": "",
    "TRACKILLEGALMONEY": "NT$0",
    "INSPECTIONDATETIMES": "",
    "PENALTYKIND": "罰鍰(非連續處罰)",
    "ISIMPORTANT": "否",
    "PAYMENTSTATE": "無分期已繳清",
    "ISREMINDER": "否",
    "ISADMINCOURT": "否",
    "IS_SERIES_FIRST": true,
    "SERIES_FIRST_DEPARTMENT_ID": "",
    "SERIES_FIRST_DEPARTMENT_NAME": "",
    "SERIES_FIRST_PENALTY_ID": "",
    "FACADDRESS": "高雄市仁武區後安里後庄巷一一七號",
    "TRANSGRESSADDRESS": "高雄市仁武區後安里後庄巷117號",
    "SUBJECT": "罰鍰新臺幣6000元整。處環境講習1小時整。",
    "GISTDEFINE": "違反廢棄物清理法第36條暨業廢棄物貯存清除處理方法及設施標準第6條第1項第4款、第10條第1項第1款規定，爰依同法第52條暨違反廢棄物清理法罰鍰額度裁罰準則（附表二項次13）規定裁處。依環境教育法第23條第2款之規定裁處環境講習",
    "ISREDUCEMONEY": "",
    "TRANSGRESSTYPE": "事業廢棄物",
    "ALLOW_REWORK_DATA": "-",
    "created_at": "2025-07-23 14:51:52"
}