{
    "REGISTRATIONNO": "P5801728",
    "FACILITYNAME": "台塑石化股份有限公司麥寮二廠",
    "COUNTY": "雲林縣",
    "COUNTYCODE": "",
    "DOCUMENTNO": "20-107-090006",
    "PENALTYYEAR": "2018",
    "PENALTYDATE": "2018\/09\/07",
    "TRANSGRESSDATE": "2018\/03\/19",
    "TRANSGRESSLAW": "空氣污染防制法第31條第1項第1款",
    "PENALTYMONEY": "NT$1,000,000",
    "ISPETITION": "否",
    "PETITIONAGENCY": "",
    "PETITIONRESULTS": "",
    "APPEALRESCIND": "",
    "UPDATETIME": "2025\/02\/04 20:30",
    "IMPROVEDEADLINE": "2018\/09\/03",
    "INSPECTIONCONDITION": "",
    "TRANSGRESSNAME": "台塑石化股份有限公司麥寮二廠",
    "TRANSGRESSCONTROLID": "P5801728",
    "TRANSGRESSSTATE": "依據「空氣污染防制法」第20條第1項規定：公私場所固定污染源排放空氣污染物，應符合排放標準。第31條第1項第1款規定：在各級防制區及總量管制區內，不得有下列行為： 一、從事燃燒、融化、煉製、研磨、鑄造、輸送或其他操作，致產生明顯之粒狀污染物，散布於空氣或他人財物。三、經查107年3月19日貴公司麥寮二廠於M01製程因爐管（E069）破裂，造成後續燃燒不完全，致產生大量明顯粒狀污染物（黑煙）由爐體及排放管道P020排放，經本局派員進行現場目測判煙結果不透光率為75％（標準為20％）；另裂解爐爐體產生大量明顯粒狀污染物，該排放未經粒狀污染物收集及處理設備，散佈於空氣中。上述行為已違反空氣污染防制法第20條第1項暨31條第1項第1款規定規定，爰依同法第56條暨60條規定，分別處分新台幣10~100萬元。",
    "ILLEGALMONEY": "NT$0",
    "ISIMPROVE": "已改善完成",
    "Source": "ERDB",
    "FACUNIFORMNO": "86522210",
    "LAWSUITDATE1": "",
    "TRACKILLEGALMONEY": "NT$0",
    "INSPECTIONDATETIMES": "",
    "PENALTYKIND": "罰鍰(非連續處罰)",
    "ISIMPORTANT": "",
    "PAYMENTSTATE": "無分期已繳清",
    "ISREMINDER": "否",
    "ISADMINCOURT": "否",
    "IS_SERIES_FIRST": true,
    "SERIES_FIRST_DEPARTMENT_ID": "",
    "SERIES_FIRST_DEPARTMENT_NAME": "",
    "SERIES_FIRST_PENALTY_ID": "",
    "FACADDRESS": "雲林縣麥寮鄉中興村台塑工業園區八號、八之五號",
    "TRANSGRESSADDRESS": "雲林縣麥寮鄉中興村台塑工業園區8號、8-5號",
    "SUBJECT": "罰鍰新臺幣1000000元整。限改日期：107年09月03日。處環境講習8小時整。",
    "GISTDEFINE": "違反空氣污染防制法第31條第1項第1款之規定，並依空氣污染防制法第60條第1項裁處。依環境教育法第23條第2款之規定裁處環境講習",
    "ISREDUCEMONEY": "",
    "TRANSGRESSTYPE": "固定空污",
    "ALLOW_REWORK_DATA": "-",
    "created_at": "2025-07-23 14:54:03"
}